DSD-midterm/q6/d_flip_flop.v
module d_flip_flop (
    input d,
    input clk,
    input reset,
    output reg q
);

always @(posedge clk, posedge reset)
begin
    if (reset)
        q <= 1'b0;
    else
        q <= d;
end

endmodule

DSD-midterm/q6/johnson_counter.v
`include "d_flip_flop.v"

module johnson_counter #(
    parameter N = 4
) (
    input clk,
    input reset,
    output [N-1:0] q
);

genvar i;
generate
    for (i = 0; i < N; i=i+1) begin : dff_loop
        d_flip_flop dff (
            .d(i == 0 ? ~q[N-1] : q[i-1]),
            .clk(clk),
            .reset(reset),
            .q(q[i])
        );
    end
endgenerate

endmodule

DSD-midterm/q6/reset_tb.v
`include "johnson_counter.v"

module parameter_tb;

parameter CLK_PERIOD    = 10;
parameter SIM_DURATION  = 100;

reg clk     = 0;
reg reset   = 0;

wire [3:0]  q;

johnson_counter #(.N(4)) dut (
    .clk(clk),
    .reset(reset),
    .q(q)
);


always #((CLK_PERIOD / 2)) clk = ~clk;

initial begin
    $dumpfile("waveform.vcd");
    $dumpvars(0, parameter_tb);
    reset = 1;
    #10
    reset = 0;
    #27
    reset = 1;
    #15
    reset = 0;

end

always @(posedge clk) begin
    if ($time >= SIM_DURATION)
        $finish;
end

endmodule

DSD-midterm/q6/waveform.vcd
$date
	Sat May 18 10:17:04 2024
$end
$version
	Icarus Verilog
$end
$timescale
	1s
$end
$scope module parameter_tb $end
$var wire 4 ! q [3:0] $end
$var parameter 32 " CLK_PERIOD $end
$var parameter 32 # SIM_DURATION $end
$var reg 1 $ clk $end
$var reg 1 % reset $end
$scope module dut $end
$var wire 1 $ clk $end
$var wire 1 % reset $end
$var wire 4 & q [3:0] $end
$var parameter 32 ' N $end
$scope begin dff_loop[0] $end
$var parameter 2 ( i $end
$scope module dff $end
$var wire 1 $ clk $end
$var wire 1 ) d $end
$var wire 1 % reset $end
$var reg 1 * q $end
$upscope $end
$upscope $end
$scope begin dff_loop[1] $end
$var parameter 2 + i $end
$scope module dff $end
$var wire 1 $ clk $end
$var wire 1 , d $end
$var wire 1 % reset $end
$var reg 1 - q $end
$upscope $end
$upscope $end
$scope begin dff_loop[2] $end
$var parameter 3 . i $end
$scope module dff $end
$var wire 1 $ clk $end
$var wire 1 / d $end
$var wire 1 % reset $end
$var reg 1 0 q $end
$upscope $end
$upscope $end
$scope begin dff_loop[3] $end
$var parameter 3 1 i $end
$scope module dff $end
$var wire 1 $ clk $end
$var wire 1 2 d $end
$var wire 1 % reset $end
$var reg 1 3 q $end
$upscope $end
$upscope $end
$upscope $end
$upscope $end
$enddefinitions $end
$comment Show the parameter values. $end
$dumpall
b11 1
b10 .
b1 +
b0 (
b100 '
b1100100 #
b1010 "
$end
#0
$dumpvars
03
02
00
0/
0-
0,
0*
1)
b0 &
1%
0$
b0 !
$end
#5
1$
#10
0$
0%
#15
1,
b1 !
b1 &
1*
1$
#20
0$
#25
1/
b11 !
b11 &
1-
1$
#30
0$
#35
12
b111 !
b111 &
10
1$
#37
02
0/
0,
00
0-
b0 !
b0 &
0*
1%
#40
0$
#45
1$
#50
0$
#52
0%
#55
1,
b1 !
b1 &
1*
1$
#60
0$
#65
1/
b11 !
b11 &
1-
1$
#70
0$
#75
12
b111 !
b111 &
10
1$
#80
0$
#85
0)
b1111 !
b1111 &
13
1$
#90
0$
#95
0,
b1110 !
b1110 &
0*
1$
#100
0$
#105
0/
b1100 !
b1100 &
0-
1$
