HW2/Q3/bidirectional_bus_gate.v
module bidirectional_bus_gate #(
    parameter N = 8
) (
    input wire [N-1:0] data_in_1,
    input wire [N-1:0] data_in_2,
    input wire oe_1,
    input wire oe_2,
    output wire [N-1:0] data_out_1,
    output wire [N-1:0] data_out_2,
    inout wire [N-1:0] bi_data
);

genvar i;
for (i = 0; i < N; i = i + 1) begin
    bufif1 #(5:6:7, 4:5:6, 4:5:6) buf1(bi_data[i], data_in_1[i], oe_1);
    bufif1 #(5:6:7, 4:5:6, 4:5:6) buf2(bi_data[i], data_in_2[i], oe_2);
    bufif1 #(5:6:7, 4:5:6, 4:5:6) buf3(data_out_1[i], bi_data[i], oe_2);
    bufif1 #(5:6:7, 4:5:6, 4:5:6) buf4(data_out_2[i], bi_data[i], oe_1);
    
end

endmodule

HW2/Q3/tb_bidirectional_bus_gate.v
`include "bidirectional_bus_gate.v"

module tb_bidirectional_bus_gate;

// Parameters for the width of the bus
parameter N = 8;

// Test inputs and outputs
reg [N-1:0] data_in_1; // Input data for port 1
reg [N-1:0] data_in_2; // Input data for port 2
reg oe_1; // Output enable for port 1
reg oe_2; // Output enable for port 2
wire [N-1:0] data_out_1; // Output data for port 1
wire [N-1:0] data_out_2; // Output data for port 2
wire [N-1:0] bi_data; // Bidirectional data bus

// Instantiate the bidirectional_bus_gate module
bidirectional_bus_gate #(.N(N)) uut (
    .data_in_1(data_in_1),
    .data_in_2(data_in_2),
    .oe_1(oe_1),
    .oe_2(oe_2),
    .data_out_1(data_out_1),
    .data_out_2(data_out_2),
    .bi_data(bi_data)
);

initial begin
    $dumpfile("waveform.vcd");
    $dumpvars(0, tb_bidirectional_bus_gate);
    // Display header for the output
    $display("Time\tOE1\tOE2\tBiData\tOut1\tOut2");

    // Test case 1: No outputs enabled, bi_data should be high-impedance
    oe_1 = 0;
    oe_2 = 0;
    data_in_1 = 8'hAA; // Example data for port 1
    data_in_2 = 8'h55; // Example data for port 2
    #10;
    $display("%0t\t%b\t%b\t%h\t%h\t%h", $time, oe_1, oe_2, bi_data, data_out_1, data_out_2);

    // Test case 2: Enable output from port 1
    oe_1 = 1;
    oe_2 = 0;
    #10; // Allow time for propagation
    $display("%0t\t%b\t%b\t%h\t%h\t%h", $time, oe_1, oe_2, bi_data, data_out_1, data_out_2);

    // Test case 3: Enable output from port 2, disabling port 1
    oe_1 = 0;
    oe_2 = 1;
    #10; // Allow time for propagation
    $display("%0t\t%b\t%b\t%h\t%h\t%h", $time, oe_1, oe_2, bi_data, data_out_1, data_out_2);

    // Test case 4: Enable both ports (should create high-impedance due to conflict)
    oe_1 = 1;
    oe_2 = 1;
    #10; // Allow time for propagation
    $display("%0t\t%b\t%b\t%h\t%h\t%h", $time, oe_1, oe_2, bi_data, data_out_1, data_out_2);

    // End the simulation
    $stop;
end

endmodule

HW2/Q3/waveform.vcd
$date
	Sun May  5 19:28:28 2024
$end
$version
	Icarus Verilog
$end
$timescale
	1s
$end
$scope module tb_bidirectional_bus_gate $end
$var wire 8 ! bi_data [7:0] $end
$var wire 8 " data_out_2 [7:0] $end
$var wire 8 # data_out_1 [7:0] $end
$var parameter 32 $ N $end
$var reg 8 % data_in_1 [7:0] $end
$var reg 8 & data_in_2 [7:0] $end
$var reg 1 ' oe_1 $end
$var reg 1 ( oe_2 $end
$scope module uut $end
$var wire 8 ) bi_data [7:0] $end
$var wire 8 * data_in_1 [7:0] $end
$var wire 8 + data_in_2 [7:0] $end
$var wire 1 ' oe_1 $end
$var wire 1 ( oe_2 $end
$var wire 8 , data_out_2 [7:0] $end
$var wire 8 - data_out_1 [7:0] $end
$var parameter 32 . N $end
$scope begin genblk1[0] $end
$var parameter 2 / i $end
$upscope $end
$scope begin genblk1[1] $end
$var parameter 2 0 i $end
$upscope $end
$scope begin genblk1[2] $end
$var parameter 3 1 i $end
$upscope $end
$scope begin genblk1[3] $end
$var parameter 3 2 i $end
$upscope $end
$scope begin genblk1[4] $end
$var parameter 4 3 i $end
$upscope $end
$scope begin genblk1[5] $end
$var parameter 4 4 i $end
$upscope $end
$scope begin genblk1[6] $end
$var parameter 4 5 i $end
$upscope $end
$scope begin genblk1[7] $end
$var parameter 4 6 i $end
$upscope $end
$upscope $end
$upscope $end
$enddefinitions $end
$comment Show the parameter values. $end
$dumpall
b111 6
b110 5
b101 4
b100 3
b11 2
b10 1
b1 0
b0 /
b1000 .
b1000 $
$end
#0
$dumpvars
bx -
bx ,
b1010101 +
b10101010 *
bx )
0(
0'
b1010101 &
b10101010 %
bx #
bx "
bx !
$end
#6
bz !
bz )
bz #
bz -
bz "
bz ,
#10
1'
#16
bz0z0z0z0 !
bz0z0z0z0 )
bx "
bx ,
#17
b10101010 !
b10101010 )
#20
1(
0'
#26
bz0z0z0z0 #
bz0z0z0z0 -
b0z0z0z0z !
b0z0z0z0z )
bz "
bz ,
#27
b1010101 !
b1010101 )
#30
1'
#32
b0 #
b0 -
#34
b1010101 #
b1010101 -
#36
b0x0x0x0x !
b0x0x0x0x )
b0z0z0z0z "
b0z0z0z0z ,
#37
bx !
bx )
