HW1/Q2/priority_encoder.v
module priority_encoder(
    input [3:0] I,
    output [1:0] O,
    output wire v
);
   assign v = I[3] | I[2] | I[1] | I[0];
   assign O[0] = (v & (I[3] | (~I[2] & I[1]))) | (~v & 1'bx);
   assign O[1] = (v & (I[3] | I[2])) | (~v & 1'bx);
   
endmodule

HW1/Q2/testbench.v
`include "priority_encoder.v"

module testbench();
    reg [3:0] I;
    wire [1:0] O;
    wire v;

    priority_encoder encoder(
        .I(I),
        .O(O),
        .v(v)
    );

    initial 
        I = 0;
    always 
        #5 I = I + 1;
    
    initial begin
        $dumpfile("waveform.vcd");
        $dumpvars(0, testbench);
        #80;
        $stop;
    end

    initial
        $monitor("I = %4b, O = %2b v = %b", I, O, v);

endmodule

HW1/Q2/waveform.vcd
$date
	Thu Apr 11 23:16:51 2024
$end
$version
	Icarus Verilog
$end
$timescale
	1s
$end
$scope module testbench $end
$var wire 1 ! v $end
$var wire 2 " O [1:0] $end
$var reg 4 # I [3:0] $end
$scope module encoder $end
$var wire 4 $ I [3:0] $end
$var wire 1 ! v $end
$var wire 2 % O [1:0] $end
$upscope $end
$upscope $end
$enddefinitions $end
$comment Show the parameter values. $end
$dumpall
$end
#0
$dumpvars
bx %
b0 $
b0 #
bx "
0!
$end
#5
b0 "
b0 %
1!
b1 #
b1 $
#10
b1 "
b1 %
1!
b10 #
b10 $
#15
b11 #
b11 $
#20
b10 "
b10 %
1!
b100 #
b100 $
#25
b101 #
b101 $
#30
b110 #
b110 $
#35
b111 #
b111 $
#40
b11 "
b11 %
b1000 #
b1000 $
#45
b1001 #
b1001 $
#50
b1010 #
b1010 $
#55
b1011 #
b1011 $
#60
b1100 #
b1100 $
#65
b1101 #
b1101 $
#70
b1110 #
b1110 $
#75
b1111 #
b1111 $
